lavalink/__init__.py
lavalink/enums.py
lavalink/errors.py
lavalink/lavalink.py
lavalink/log.py
lavalink/node.py
lavalink/player.py
lavalink/rest_api.py
lavalink/utils.py
Red_Lavalink-0.11.0.dist-info/LICENSE
Red_Lavalink-0.11.0.dist-info/METADATA
Red_Lavalink-0.11.0.dist-info/WHEEL
Red_Lavalink-0.11.0.dist-info/top_level.txt
Red_Lavalink-0.11.0.dist-info/RECORD
