Metadata-Version: 2.1
Name: Red-Lavalink
Version: 0.11.0
Summary: Lavalink client library for Red-DiscordBot
Author: Cog Creators, tekulvw
Project-URL: Homepage, https://github.com/Cog-Creators/Red-Lavalink
Project-URL: Discord Server, https://discord.gg/red
Project-URL: Documentation, https://red-lavalink.readthedocs.io
Project-URL: Donate on Patreon, https://www.patreon.com/Red_Devs
Project-URL: Issue Tracker, https://github.com/Cog-Creators/Red-Lavalink/issues
Project-URL: Source Code, https://github.com/Cog-Creators/Red-Lavalink
Classifier: Development Status :: 5 - Production/Stable
Classifier: Framework :: AsyncIO
Classifier: Intended Audience :: Developers
Classifier: License :: OSI Approved :: GNU General Public License v3 (GPLv3)
Classifier: Operating System :: OS Independent
Classifier: Programming Language :: Python :: 3 :: Only
Classifier: Programming Language :: Python :: 3.8
Classifier: Programming Language :: Python :: 3.9
Classifier: Programming Language :: Python :: 3.10
Classifier: Programming Language :: Python :: 3.11
Classifier: Topic :: Multimedia :: Sound/Audio :: Players
Classifier: Topic :: Software Development :: Libraries :: Python Modules
Requires-Python: >=3.8.1
License-File: LICENSE
Requires-Dist: aiohttp (>=3.6.0)
Requires-Dist: discord.py (>=2.0.0)
Requires-Dist: Red-Commons (<2,>=1.0.0)
Provides-Extra: doc
Requires-Dist: sphinx ; extra == 'doc'
Requires-Dist: sphinxcontrib-trio ; extra == 'doc'
Requires-Dist: sphinx-rtd-theme ; extra == 'doc'
Provides-Extra: test
Requires-Dist: pytest (>=7) ; extra == 'test'
Requires-Dist: pytest-asyncio (>=0.19) ; extra == 'test'
